README.md
setup.py
ckx/__init__.py
ckx/__main__.py
ckx/cli.py
ckx.egg-info/PKG-INFO
ckx.egg-info/SOURCES.txt
ckx.egg-info/dependency_links.txt
ckx.egg-info/entry_points.txt
ckx.egg-info/not-zip-safe
ckx.egg-info/top_level.txt