Metadata-Version: 2.1
Name: ckx
Version: 0.0.1
Summary: CK-X
Home-page: UNKNOWN
Author: 
Author-email: 
License: UNKNOWN
Platform: UNKNOWN
